<?xml version="1.0" encoding="UTF-8"?>
<!--
     Copyright (c) 2008, 2012 Mirko Raner and others
     All rights reserved. This program and the accompanying materials
     are made available under the terms of the Eclipse Public License v1.0
     which accompanies this distribution, and is available at
     http://www.eclipse.org/legal/epl-v10.html
     
     Contributors:
     Mirko Raner - initial implementation for Eclipse Bug 196337
     Martin Oberhuber (Wind River) - Import to Eclipse TM
 -->
<feature
      id="org.eclipse.tm.terminal.local"
      label="%featureName"
      version="0.2.400.qualifier"
      provider-name="%providerName"
      image="eclipse_update_120.jpg">

   <description>
      %description
   </description>

   <copyright>
      %copyright
   </copyright>

   <license url="%licenseURL">
      %license
   </license>

   <url>
      <update label="%tmUpdateSiteName" url="http://download.eclipse.org/tm/updates/3.5"/>
      <discovery label="%tmUpdateSiteName" url="http://download.eclipse.org/tm/updates/3.5"/>
   </url>

   <requires>
      <import plugin="org.eclipse.core.runtime"/>
      <import plugin="org.eclipse.debug.core"/>
      <import plugin="org.eclipse.debug.ui"/>
      <import plugin="org.eclipse.jface"/>
      <import plugin="org.eclipse.ui"/>
      <import plugin="org.eclipse.ui.externaltools"/>
      <import feature="org.eclipse.cdt.platform" version="7.0.0" match="greaterOrEqual"/>
      <import plugin="org.eclipse.tm.terminal" version="3.2.0" match="equivalent"/>
      <import plugin="org.eclipse.cdt.core" version="5.2.0" match="compatible"/>
      <import plugin="org.eclipse.core.variables"/>
   </requires>

   <plugin
         id="org.eclipse.tm.terminal.local"
         download-size="18"
         install-size="47"
         version="0.0.0"
         unpack="false"/>

</feature>
