<?xml version="1.0" encoding="UTF-8"?>
<feature
      id="org.eclipse.dd.dsf.sdk"
      label="Debugger Services Framework end-user and extender SDK"
      version="1.1.0.qualifier"
      provider-name="Eclipse.org">

   <description url="http://www.eclipse.org/dsdp/dd/">
      Device Software Development Platform Project
Device Debug
Debug Services Framework
Core SDK
   </description>

   <copyright>
      %copyright
   </copyright>

   <license url="%licenseURL">
      %license
   </license>

   <url>
      <update label="Device Debug" url="http://download.eclipse.org/dsdp/dd/updates"/>
   </url>

   <requires>
      <import plugin="org.eclipse.core.runtime"/>
      <import plugin="org.eclipse.debug.core"/>
      <import plugin="org.eclipse.ui"/>
      <import plugin="org.eclipse.debug.ui"/>
   </requires>

   <plugin
         id="org.eclipse.dd.dsf"
         download-size="0"
         install-size="0"
         version="0.0.0"
         unpack="false"/>

   <plugin
         id="org.eclipse.dd.dsf.ui"
         download-size="0"
         install-size="0"
         version="0.0.0"
         unpack="false"/>

   <plugin
         id="org.eclipse.dd.dsf.debug"
         download-size="0"
         install-size="0"
         version="0.0.0"
         unpack="false"/>

   <plugin
         id="org.eclipse.dd.dsf.debug.ui"
         download-size="0"
         install-size="0"
         version="0.0.0"
         unpack="false"/>

</feature>
